clabe_pydantic2/__init__.py
clabe_pydantic2/banks.py
clabe_pydantic2/errors.py
clabe_pydantic2/types.py
clabe_pydantic2/validations.py
clabe_pydantic2/version.py
clabe_pydantic2-0.1.2.dist-info/LICENSE
clabe_pydantic2-0.1.2.dist-info/METADATA
clabe_pydantic2-0.1.2.dist-info/WHEEL
clabe_pydantic2-0.1.2.dist-info/RECORD
