Metadata-Version: 2.1
Name: clabe_pydantic2
Version: 0.1.2
Summary: 
Author: Maksim Dyurdeev
Author-email: m.dyurdeev@ya.ru
Requires-Python: >=3.11,<4.0
Classifier: Programming Language :: Python :: 3
Classifier: Programming Language :: Python :: 3.11
Classifier: Programming Language :: Python :: 3.12
Requires-Dist: pydantic (>=2.7.1,<3.0.0)
